<?xml version="1.0" encoding="utf-8"?>
<xml>
	<head expect="14142" updatetime="2014-10-14 08:10:45" fsendtime="2014-10-10 22:55" shenheprocess="1" />
	<row ordernum="1" hometeam="荷&amp;nbsp;&amp;nbsp;兰" guestteam="哈萨克" homescore="3" guestscore="1" resultscore="10-11 02:45" result="3" fixtureid="455266" actionid="1000014142" plurl="1.05&amp;nbsp;11.56&amp;nbsp;31.90" freviewid="10014142101" hometeamid="18" guestteamid="108" stageid="7634" seasonid="3102" stagemode="2" homestanding="5" gueststanding="4" asian="0.66&amp;nbsp;三球/三球半&amp;nbsp;1.16" handvalue="-3.25" winkl="0.94" drawkl="0.94" lostkl="0.98" winls="8.07" drawls="285.23" lostls="1648.90" backcolor="#6F006F" simplegbname="欧洲杯" matchround="0" stagegbname="外围赛" matchid="105" isright="1" matchgbname="欧洲国家杯" hometeamname="荷兰" guestteamname="哈萨克斯坦"/>
	<row ordernum="2" hometeam="土耳其" guestteam="捷&amp;nbsp;&amp;nbsp;克" homescore="1" guestscore="2" resultscore="10-11 02:45" result="0" fixtureid="455267" actionid="1000014142" plurl="2.29&amp;nbsp;3.17&amp;nbsp;3.13" freviewid="10014142102" hometeamid="17" guestteamid="22" stageid="7634" seasonid="3102" stagemode="2" homestanding="6" gueststanding="2" asian="1.10&amp;nbsp;平手/半球&amp;nbsp;0.72" handvalue="-0.25" winkl="0.94" drawkl="0.93" lostkl="0.93" winls="55.48" drawls="13.34" lostls="50.70" backcolor="#6F006F" simplegbname="欧洲杯" matchround="0" stagegbname="外围赛" matchid="105" isright="1" matchgbname="欧洲国家杯" hometeamname="土耳其" guestteamname="捷克"/>
	<row ordernum="3" hometeam="比利时" guestteam="安道尔" homescore="6" guestscore="0" resultscore="10-11 02:45" result="3" fixtureid="455274" actionid="1000014142" plurl="1.01&amp;nbsp;19.29&amp;nbsp;45.64" freviewid="10014142103" hometeamid="23" guestteamid="137" stageid="7634" seasonid="3102" stagemode="2" homestanding="3" gueststanding="6" asian="0.74&amp;nbsp;四球&amp;nbsp;1.08" handvalue="-4" winkl="0.94" drawkl="0.96" lostkl="0.98" winls="0.44" drawls="849.74" lostls="2214.26" backcolor="#6F006F" simplegbname="欧洲杯" matchround="0" stagegbname="外围赛" matchid="105" isright="1" matchgbname="欧洲国家杯" hometeamname="比利时" guestteamname="安道尔"/>
	<row ordernum="4" hometeam="塞浦路" guestteam="以色列" homescore="1" guestscore="2" resultscore="10-11 02:45" result="0" fixtureid="455275" actionid="1000014142" plurl="3.53&amp;nbsp;3.21&amp;nbsp;2.09" freviewid="10014142104" hometeamid="84" guestteamid="51" stageid="7634" seasonid="3102" stagemode="2" homestanding="2" gueststanding="4" asian="0.78&amp;nbsp;受半球&amp;nbsp;1.04" handvalue="0.5" winkl="0.93" drawkl="0.93" lostkl="0.93" winls="37.12" drawls="7.18" lostls="10.67" backcolor="#6F006F" simplegbname="欧洲杯" matchround="0" stagegbname="外围赛" matchid="105" isright="1" matchgbname="欧洲国家杯" hometeamname="塞浦路斯" guestteamname="以色列"/>
	<row ordernum="5" hometeam="威尔士" guestteam="波&amp;nbsp;&amp;nbsp;黑" homescore="0" guestscore="0" resultscore="10-11 02:45" result="1" fixtureid="455276" actionid="1000014142" plurl="3.18&amp;nbsp;3.23&amp;nbsp;2.22" freviewid="10014142105" hometeamid="62" guestteamid="80" stageid="7634" seasonid="3102" stagemode="2" homestanding="1" gueststanding="5" asian="0.86&amp;nbsp;受平手/半球&amp;nbsp;0.96" handvalue="0.25" winkl="0.93" drawkl="0.93" lostkl="0.93" winls="25.84" drawls="10.61" lostls="11.75" backcolor="#6F006F" simplegbname="欧洲杯" matchround="0" stagegbname="外围赛" matchid="105" isright="1" matchgbname="欧洲国家杯" hometeamname="威尔士" guestteamname="波黑"/>
	<row ordernum="6" hometeam="保加利" guestteam="克罗地" homescore="0" guestscore="1" resultscore="10-11 02:45" result="0" fixtureid="455327" actionid="1000014142" plurl="3.50&amp;nbsp;3.19&amp;nbsp;2.12" freviewid="10014142106" hometeamid="43" guestteamid="36" stageid="7634" seasonid="3102" stagemode="2" homestanding="3" gueststanding="2" asian="0.84&amp;nbsp;受半球&amp;nbsp;0.98" handvalue="0.5" winkl="0.94" drawkl="0.93" lostkl="0.93" winls="103.43" drawls="7.13" lostls="24.62" backcolor="#6F006F" simplegbname="欧洲杯" matchround="0" stagegbname="外围赛" matchid="105" isright="1" matchgbname="欧洲国家杯" hometeamname="保加利亚" guestteamname="克罗地亚"/>
	<row ordernum="7" hometeam="意大利" guestteam="阿塞拜" homescore="2" guestscore="1" resultscore="10-11 02:45" result="3" fixtureid="455328" actionid="1000014142" plurl="1.07&amp;nbsp;9.95&amp;nbsp;25.73" freviewid="10014142107" hometeamid="19" guestteamid="110" stageid="7634" seasonid="3102" stagemode="2" homestanding="1" gueststanding="4" asian="0.86&amp;nbsp;两球半&amp;nbsp;0.96" handvalue="-2.5" winkl="0.93" drawkl="0.93" lostkl="0.95" winls="2.49" drawls="92.33" lostls="834.55" backcolor="#6F006F" simplegbname="欧洲杯" matchround="0" stagegbname="外围赛" matchid="105" isright="1" matchgbname="欧洲国家杯" hometeamname="意大利" guestteamname="阿塞拜疆"/>
	<row ordernum="8" hometeam="马耳他" guestteam="挪&amp;nbsp;&amp;nbsp;威" homescore="0" guestscore="3" resultscore="10-11 02:45" result="0" fixtureid="455329" actionid="1000014142" plurl="8.01&amp;nbsp;4.29&amp;nbsp;1.40" freviewid="10014142108" hometeamid="119" guestteamid="31" stageid="7634" seasonid="3102" stagemode="2" homestanding="6" gueststanding="5" asian="1.00&amp;nbsp;受一球&amp;nbsp;0.82" handvalue="1" winkl="0.93" drawkl="0.93" lostkl="0.93" winls="70.25" drawls="53.65" lostls="19.06" backcolor="#6F006F" simplegbname="欧洲杯" matchround="0" stagegbname="外围赛" matchid="105" isright="1" matchgbname="欧洲国家杯" hometeamname="马耳他" guestteamname="挪威"/>
	<row ordernum="9" hometeam="苏格兰" guestteam="格鲁吉" homescore="1" guestscore="0" resultscore="10-11 23:59" result="3" fixtureid="455293" actionid="1000014142" plurl="1.67&amp;nbsp;3.53&amp;nbsp;5.31" freviewid="10014142109" hometeamid="56" guestteamid="77" stageid="7634" seasonid="3102" stagemode="2" homestanding="4" gueststanding="5" asian="0.90&amp;nbsp;半球/一球&amp;nbsp;0.92" handvalue="-0.75" winkl="0.93" drawkl="0.93" lostkl="0.94" winls="14.51" drawls="16.95" lostls="152.34" backcolor="#6F006F" simplegbname="欧洲杯" matchround="0" stagegbname="外围赛" matchid="105" isright="1" matchgbname="欧洲国家杯" hometeamname="苏格兰" guestteamname="格鲁吉亚"/>
	<row ordernum="10" hometeam="罗马尼" guestteam="匈牙利" homescore="1" guestscore="1" resultscore="10-11 23:59" result="1" fixtureid="455310" actionid="1000014142" plurl="1.71&amp;nbsp;3.47&amp;nbsp;4.99" freviewid="10014142110" hometeamid="26" guestteamid="55" stageid="7634" seasonid="3102" stagemode="2" homestanding="3" gueststanding="4" asian="0.86&amp;nbsp;半球/一球&amp;nbsp;0.96" handvalue="-0.75" winkl="0.95" drawkl="0.93" lostkl="0.94" winls="763.95" drawls="30.88" lostls="279.84" backcolor="#6F006F" simplegbname="欧洲杯" matchround="0" stagegbname="外围赛" matchid="105" isright="1" matchgbname="欧洲国家杯" hometeamname="罗马尼亚" guestteamname="匈牙利"/>
	<row ordernum="11" hometeam="亚美尼" guestteam="塞尔维" homescore="1" guestscore="1" resultscore="10-11 23:59" result="1" fixtureid="455335" actionid="1000014142" plurl="4.88&amp;nbsp;3.51&amp;nbsp;1.73" freviewid="10014142111" hometeamid="101" guestteamid="4" stageid="7634" seasonid="3102" stagemode="2" homestanding="4" gueststanding="3" asian="0.88&amp;nbsp;受一球&amp;nbsp;0.94" handvalue="1" winkl="0.99" drawkl="0.95" lostkl="0.92" winls="394.26" drawls="54.81" lostls="115.17" backcolor="#6F006F" simplegbname="欧洲杯" matchround="0" stagegbname="外围赛" matchid="105" isright="1" matchgbname="欧洲国家杯" hometeamname="亚美尼亚" guestteamname="塞尔维亚"/>
	<row ordernum="12" hometeam="波&amp;nbsp;&amp;nbsp;兰" guestteam="德&amp;nbsp;&amp;nbsp;国" homescore="2" guestscore="0" resultscore="10-12 02:45" result="3" fixtureid="455294" actionid="1000014142" plurl="5.73&amp;nbsp;3.94&amp;nbsp;1.56" freviewid="10014142112" hometeamid="37" guestteamid="13" stageid="7634" seasonid="3102" stagemode="2" homestanding="1" gueststanding="2" asian="1.00&amp;nbsp;受半球/一球&amp;nbsp;0.82" handvalue="0.75" winkl="0.93" drawkl="0.93" lostkl="0.94" winls="88.32" drawls="25.15" lostls="23.41" backcolor="#6F006F" simplegbname="欧洲杯" matchround="0" stagegbname="外围赛" matchid="105" isright="1" matchgbname="欧洲国家杯" hometeamname="波兰" guestteamname="德国"/>
	<row ordernum="13" hometeam="芬&amp;nbsp;&amp;nbsp;兰" guestteam="希&amp;nbsp;&amp;nbsp;腊" homescore="1" guestscore="1" resultscore="10-12 02:45" result="1" fixtureid="455311" actionid="1000014142" plurl="2.79&amp;nbsp;3.04&amp;nbsp;2.63" freviewid="10014142113" hometeamid="44" guestteamid="49" stageid="7634" seasonid="3102" stagemode="2" homestanding="1" gueststanding="5" asian="0.78&amp;nbsp;平手&amp;nbsp;1.04" handvalue="0" winkl="0.94" drawkl="0.94" lostkl="0.94" winls="74.90" drawls="15.53" lostls="135.58" backcolor="#6F006F" simplegbname="欧洲杯" matchround="0" stagegbname="外围赛" matchid="105" isright="1" matchgbname="欧洲国家杯" hometeamname="芬兰" guestteamname="希腊"/>
	<row ordernum="14" hometeam="阿尔巴" guestteam="丹&amp;nbsp;&amp;nbsp;麦" homescore="1" guestscore="1" resultscore="10-12 02:45" result="1" fixtureid="455336" actionid="1000014142" plurl="3.40&amp;nbsp;3.17&amp;nbsp;2.15" freviewid="10014142114" hometeamid="96" guestteamid="3" stageid="7634" seasonid="3102" stagemode="2" homestanding="2" gueststanding="1" asian="1.02&amp;nbsp;受平手/半球&amp;nbsp;0.80" handvalue="0.25" winkl="0.93" drawkl="0.93" lostkl="0.93" winls="51.19" drawls="11.89" lostls="12.73" backcolor="#6F006F" simplegbname="欧洲杯" matchround="0" stagegbname="外围赛" matchid="105" isright="1" matchgbname="欧洲国家杯" hometeamname="阿尔巴尼亚" guestteamname="丹麦"/>
</xml>