<?xml version="1.0" encoding="utf-8"?>
<xml>
	<head expect="16118" updatetime="2016-08-17 15:47:14" fsendtime="2016-08-13 21:25" shenheprocess="1" />
	<row ordernum="1" hometeam="伯恩利" guestteam="斯旺西" homescore="0" guestscore="1" resultscore="08-13 22:00" result="0" fixtureid="572726" actionid="1000016118" plurl="2.64&amp;nbsp;3.13&amp;nbsp;2.84" freviewid="10016118101" hometeamid="700" guestteamid="511" stageid="9848" seasonid="3822" stagemode="1" homestanding="13" gueststanding="18" asian="0.92&amp;nbsp;平手&amp;nbsp;0.94" handvalue="0" winkl="0.95" drawkl="0.95" lostkl="0.95" winls="32.16" drawls="8.97" lostls="18.63" backcolor="#FF1717" simplegbname="英超" matchround="1" stagegbname="联赛赛程" matchid="106" isright="1" matchgbname="英格兰超级联赛" hometeamname="伯恩利" guestteamname="斯旺西"/>
	<row ordernum="2" hometeam="水晶宫" guestteam="西布罗" homescore="0" guestscore="1" resultscore="08-13 22:00" result="0" fixtureid="572732" actionid="1000016118" plurl="2.09&amp;nbsp;3.16&amp;nbsp;3.90" freviewid="10016118102" hometeamid="516" guestteamid="1284" stageid="9848" seasonid="3822" stagemode="1" homestanding="17" gueststanding="3" asian="0.84&amp;nbsp;平手/半球&amp;nbsp;1.02" handvalue="-0.25" winkl="0.95" drawkl="0.95" lostkl="0.95" winls="21.68" drawls="8.13" lostls="34.66" backcolor="#FF1717" simplegbname="英超" matchround="1" stagegbname="联赛赛程" matchid="106" isright="1" matchgbname="英格兰超级联赛" hometeamname="水晶宫" guestteamname="西布罗姆维奇"/>
	<row ordernum="3" hometeam="埃弗顿" guestteam="热&amp;nbsp;刺" homescore="1" guestscore="1" resultscore="08-13 22:00" result="1" fixtureid="572733" actionid="1000016118" plurl="3.27&amp;nbsp;3.33&amp;nbsp;2.25" freviewid="10016118103" hometeamid="565" guestteamid="1238" stageid="9848" seasonid="3822" stagemode="1" homestanding="15" gueststanding="5" asian="1.02&amp;nbsp;受平手/半球&amp;nbsp;0.84" handvalue="0.25" winkl="0.95" drawkl="0.95" lostkl="0.95" winls="63.09" drawls="10.90" lostls="25.39" backcolor="#FF1717" simplegbname="英超" matchround="1" stagegbname="联赛赛程" matchid="106" isright="1" matchgbname="英格兰超级联赛" hometeamname="埃弗顿" guestteamname="托特纳姆热刺"/>
	<row ordernum="4" hometeam="米德尔" guestteam="斯托克" homescore="1" guestscore="1" resultscore="08-13 22:00" result="1" fixtureid="572728" actionid="1000016118" plurl="2.23&amp;nbsp;3.18&amp;nbsp;3.46" freviewid="10016118104" hometeamid="1095" guestteamid="1197" stageid="9848" seasonid="3822" stagemode="1" homestanding="9" gueststanding="6" asian="0.82&amp;nbsp;平手/半球&amp;nbsp;1.04" handvalue="-0.25" winkl="0.95" drawkl="0.95" lostkl="0.95" winls="11.62" drawls="9.37" lostls="30.60" backcolor="#FF1717" simplegbname="英超" matchround="1" stagegbname="联赛赛程" matchid="106" isright="1" matchgbname="英格兰超级联赛" hometeamname="米德尔斯堡" guestteamname="斯托克城"/>
	<row ordernum="5" hometeam="南安普" guestteam="沃特福" homescore="1" guestscore="1" resultscore="08-13 22:00" result="1" fixtureid="572729" actionid="1000016118" plurl="1.78&amp;nbsp;3.59&amp;nbsp;4.72" freviewid="10016118105" hometeamid="1128" guestteamid="1274" stageid="9848" seasonid="3822" stagemode="1" homestanding="8" gueststanding="4" asian="0.98&amp;nbsp;半球/一球&amp;nbsp;0.88" handvalue="-0.75" winkl="0.95" drawkl="0.95" lostkl="0.95" winls="10.16" drawls="20.35" lostls="24.38" backcolor="#FF1717" simplegbname="英超" matchround="1" stagegbname="联赛赛程" matchid="106" isright="1" matchgbname="英格兰超级联赛" hometeamname="南安普敦" guestteamname="沃特福德"/>
	<row ordernum="6" hometeam="曼&amp;nbsp;城" guestteam="桑德兰" homescore="2" guestscore="1" resultscore="08-14 00:30" result="3" fixtureid="572727" actionid="1000016118" plurl="1.23&amp;nbsp;6.20&amp;nbsp;12.78" freviewid="10016118106" hometeamid="1072" guestteamid="466" stageid="9848" seasonid="3822" stagemode="1" homestanding="11" gueststanding="19" asian="0.96&amp;nbsp;球半/两球&amp;nbsp;0.90" handvalue="-1.75" winkl="0.95" drawkl="0.95" lostkl="0.95" winls="5.87" drawls="45.73" lostls="155.94" backcolor="#FF1717" simplegbname="英超" matchround="1" stagegbname="联赛赛程" matchid="106" isright="1" matchgbname="英格兰超级联赛" hometeamname="曼彻斯特城" guestteamname="桑德兰"/>
	<row ordernum="7" hometeam="巴恩斯" guestteam="德比郡" homescore="2" guestscore="0" resultscore="08-13 22:00" result="3" fixtureid="577543" actionid="1000016118" plurl="3.59&amp;nbsp;3.36&amp;nbsp;2.03" freviewid="10016118107" hometeamid="640" guestteamid="760" stageid="9874" seasonid="3840" stagemode="1" homestanding="22" gueststanding="14" asian="0.78&amp;nbsp;受半球&amp;nbsp;1.04" handvalue="0.5" winkl="0.93" drawkl="0.94" lostkl="0.93" winls="23.21" drawls="14.90" lostls="6.94" backcolor="#CC3300" simplegbname="英冠" matchround="2" stagegbname="联赛赛程" matchid="62" isright="1" matchgbname="英格兰冠军联赛" hometeamname="巴恩斯利" guestteamname="德比郡"/>
	<row ordernum="8" hometeam="布伦特" guestteam="伊普斯" homescore="2" guestscore="0" resultscore="08-13 22:00" result="3" fixtureid="577547" actionid="1000016118" plurl="2.45&amp;nbsp;3.24&amp;nbsp;2.84" freviewid="10016118108" hometeamid="1361" guestteamid="1314" stageid="9874" seasonid="3840" stagemode="1" homestanding="18" gueststanding="4" asian="0.98&amp;nbsp;平手/半球&amp;nbsp;0.84" handvalue="-0.25" winkl="0.93" drawkl="0.94" lostkl="0.94" winls="19.35" drawls="9.52" lostls="14.36" backcolor="#CC3300" simplegbname="英冠" matchround="2" stagegbname="联赛赛程" matchid="62" isright="1" matchgbname="英格兰冠军联赛" hometeamname="布伦特福德" guestteamname="伊普斯维奇"/>
	<row ordernum="9" hometeam="诺维奇" guestteam="谢周三" homescore="0" guestscore="0" resultscore="08-14 00:30" result="1" fixtureid="577548" actionid="1000016118" plurl="1.90&amp;nbsp;3.36&amp;nbsp;4.09" freviewid="10016118109" hometeamid="1144" guestteamid="1300" stageid="9874" seasonid="3840" stagemode="1" homestanding="2" gueststanding="7" asian="0.92&amp;nbsp;半球&amp;nbsp;0.90" handvalue="-0.5" winkl="0.94" drawkl="0.94" lostkl="0.94" winls="6.45" drawls="10.13" lostls="52.09" backcolor="#CC3300" simplegbname="英冠" matchround="2" stagegbname="联赛赛程" matchid="62" isright="1" matchgbname="英格兰冠军联赛" hometeamname="诺维奇" guestteamname="谢菲尔德星期三"/>
	<row ordernum="10" hometeam="波尔多" guestteam="埃蒂安" homescore="3" guestscore="2" resultscore="08-13 23:00" result="3" fixtureid="573785" actionid="1000016118" plurl="2.37&amp;nbsp;3.03&amp;nbsp;3.24" freviewid="10016118110" hometeamid="693" guestteamid="494" stageid="9854" seasonid="3826" stagemode="1" homestanding="17" gueststanding="19" asian="0.96&amp;nbsp;平手/半球&amp;nbsp;0.88" handvalue="-0.25" winkl="0.94" drawkl="0.94" lostkl="0.94" winls="10.30" drawls="6.45" lostls="35.12" backcolor="#663333" simplegbname="法甲" matchround="1" stagegbname="联赛赛程" matchid="107" isright="1" matchgbname="法国甲级联赛" hometeamname="波尔多" guestteamname="圣埃蒂安"/>
	<row ordernum="11" hometeam="第&amp;nbsp;戎" guestteam="南&amp;nbsp;特" homescore="0" guestscore="1" resultscore="08-14 02:00" result="0" fixtureid="573783" actionid="1000016118" plurl="2.47&amp;nbsp;2.97&amp;nbsp;3.12" freviewid="10016118111" hometeamid="774" guestteamid="1129" stageid="9854" seasonid="3826" stagemode="1" homestanding="17" gueststanding="8" asian="1.06&amp;nbsp;平手/半球&amp;nbsp;0.78" handvalue="-0.25" winkl="0.94" drawkl="0.94" lostkl="0.94" winls="9.45" drawls="6.75" lostls="14.81" backcolor="#663333" simplegbname="法甲" matchround="1" stagegbname="联赛赛程" matchid="107" isright="1" matchgbname="法国甲级联赛" hometeamname="第戎" guestteamname="南特"/>
	<row ordernum="12" hometeam="梅&amp;nbsp;斯" guestteam="里&amp;nbsp;尔" homescore="3" guestscore="2" resultscore="08-14 02:00" result="3" fixtureid="573784" actionid="1000016118" plurl="3.55&amp;nbsp;3.05&amp;nbsp;2.21" freviewid="10016118112" hometeamid="1084" guestteamid="998" stageid="9854" seasonid="3826" stagemode="1" homestanding="10" gueststanding="12" asian="0.96&amp;nbsp;受平手/半球&amp;nbsp;0.88" handvalue="0.25" winkl="0.94" drawkl="0.94" lostkl="0.94" winls="38.22" drawls="6.15" lostls="14.11" backcolor="#663333" simplegbname="法甲" matchround="1" stagegbname="联赛赛程" matchid="107" isright="1" matchgbname="法国甲级联赛" hometeamname="梅斯" guestteamname="里尔"/>
	<row ordernum="13" hometeam="蒙彼利" guestteam="昂&amp;nbsp;热" homescore="1" guestscore="0" resultscore="08-14 02:00" result="3" fixtureid="573786" actionid="1000016118" plurl="1.89&amp;nbsp;3.18&amp;nbsp;4.66" freviewid="10016118113" hometeamid="1090" guestteamid="597" stageid="9854" seasonid="3826" stagemode="1" homestanding="9" gueststanding="18" asian="1.12&amp;nbsp;半球/一球&amp;nbsp;0.72" handvalue="-0.75" winkl="0.94" drawkl="0.94" lostkl="0.95" winls="12.26" drawls="8.36" lostls="99.65" backcolor="#663333" simplegbname="法甲" matchround="1" stagegbname="联赛赛程" matchid="107" isright="1" matchgbname="法国甲级联赛" hometeamname="蒙彼利埃" guestteamname="昂热"/>
	<row ordernum="14" hometeam="卡&amp;nbsp;昂" guestteam="洛里昂" homescore="3" guestscore="2" resultscore="08-14 02:00" result="3" fixtureid="573790" actionid="1000016118" plurl="2.22&amp;nbsp;3.19&amp;nbsp;3.36" freviewid="10016118114" hometeamid="908" guestteamid="980" stageid="9854" seasonid="3826" stagemode="1" homestanding="16" gueststanding="15" asian="0.96&amp;nbsp;平手/半球&amp;nbsp;0.88" handvalue="-0.25" winkl="0.94" drawkl="0.94" lostkl="0.94" winls="15.39" drawls="7.37" lostls="17.22" backcolor="#663333" simplegbname="法甲" matchround="1" stagegbname="联赛赛程" matchid="107" isright="1" matchgbname="法国甲级联赛" hometeamname="卡昂" guestteamname="洛里昂"/>
</xml>